yaml2ical/__init__.py
yaml2ical/cli.py
yaml2ical/ical.py
yaml2ical/index.py
yaml2ical/meeting.py
yaml2ical/recurrence.py
yaml2ical/tests/__init__.py
yaml2ical/tests/sample_data.py
yaml2ical/tests/test_index.py
yaml2ical/tests/test_meeting.py
yaml2ical/tests/test_meeting_recurrence.py
yaml2ical/tests/test_recurrence.py
yaml2ical-0.14.0.dist-info/licenses/AUTHORS
yaml2ical-0.14.0.dist-info/licenses/LICENSE
yaml2ical-0.14.0.dist-info/METADATA
yaml2ical-0.14.0.dist-info/WHEEL
yaml2ical-0.14.0.dist-info/entry_points.txt
yaml2ical-0.14.0.dist-info/pbr.json
yaml2ical-0.14.0.dist-info/top_level.txt
yaml2ical-0.14.0.dist-info/RECORD
