Metadata-Version: 2.4
Name: yaml2ical
Version: 0.14.0
Summary: Convert YAML meeting descriptions into iCalendar files
Author-email: OpenDev Contributors <service-discuss@lists.opendev.org>, NDSU IBM Capstone <service-discuss@lists.opendev.org>
License-Expression: Apache-2.0
Project-URL: Browse Source, https://opendev.org/opendev/yaml2ical
Project-URL: Bug Reporting, https://storyboard.openstack.org/#!/project/opendev/yaml2ical
Project-URL: Documentation, https://opendev.org/opendev/yaml2ical/src/branch/master/README.rst
Project-URL: Git Clone URL, https://opendev.org/opendev/yaml2ical
Project-URL: License Texts, https://opendev.org/opendev/yaml2ical/src/branch/master/LICENSE
Classifier: Intended Audience :: Information Technology
Classifier: Intended Audience :: System Administrators
Classifier: Operating System :: POSIX :: Linux
Classifier: Programming Language :: Python
Classifier: Programming Language :: Python :: 3.9
Classifier: Programming Language :: Python :: 3.10
Classifier: Programming Language :: Python :: 3.11
Classifier: Programming Language :: Python :: 3.12
Requires-Python: >=3.9
License-File: LICENSE
License-File: AUTHORS
Requires-Dist: Jinja2>=2.8
Requires-Dist: PyYAML>=3.1.0
Requires-Dist: icalendar
Requires-Dist: pbr>=1.6
Requires-Dist: pytz
Provides-Extra: test-linters
Requires-Dist: hacking<8,>=7; extra == "test-linters"
Provides-Extra: test-unit
Requires-Dist: coverage>=3.6; extra == "test-unit"
Requires-Dist: fixtures>=3.0.0; extra == "test-unit"
Requires-Dist: python-subunit>=0.0.18; extra == "test-unit"
Requires-Dist: stestr>=1.0.0; extra == "test-unit"
Requires-Dist: testtools>=1.4.0; extra == "test-unit"
Dynamic: license-file
